dele_gator-0.1.0.dist-info/METADATA
dele_gator-0.1.0.dist-info/RECORD
dele_gator-0.1.0.dist-info/WHEEL
dele_gator-0.1.0.dist-info/top_level.txt
delegator/__init__.py
