Metadata-Version: 2.1
Name: dele-gator
Version: 0.1.0
Summary: delegator is a micro-package for defining delegated methods and attributes.
Home-page: http://github.com/IwoHerka/delegator
Author: Iwo Herka
Author-email: hi@iwoherka.eu
Maintainer: Iwo Herka
Maintainer-email: hi@iwoherka.eu
License: MIT
Platform: UNKNOWN
Classifier: Development Status :: 3 - Alpha
Classifier: Intended Audience :: Developers
Classifier: License :: OSI Approved :: MIT License
Classifier: Programming Language :: Python
Classifier: Topic :: Software Development :: Libraries :: Python Modules
Requires: python (>= 3.5)
Provides: delegator
